[
  { "id": "circle", "label": "Pattern A", "file": "img-circle.svg" },
  { "id": "square", "label": "Pattern B", "file": "img-square.svg" },
  { "id": "triangle", "label": "Pattern C", "file": "img-triangle.svg" },
  { "id": "diamond", "label": "Pattern D", "file": "img-diamond.svg" },
  { "id": "hexagon", "label": "Pattern E", "file": "img-hexagon.svg" },
  { "id": "cross", "label": "Pattern F", "file": "img-cross.svg" },
  { "id": "wave", "label": "Pattern G", "file": "img-wave.svg" },
  { "id": "double", "label": "Pattern H", "file": "img-double.svg" },
  { "id": "pattern9", "label": "Pattern I", "file": "img-pattern9.svg" },
  { "id": "pattern10", "label": "Pattern J", "file": "img-pattern10.svg" }
]
